{
  "title": "Débouchage Belcodène 13720 — Intervention urgence canalisations",
  "slug": "debouchage-belcodene",
  "type": "ville",
  "ville": "Belcodène",
  "code_postal": "13720",
  "status": "published",
  "meta": {
    "title": "Débouchage Belcodène 13720 — Intervention urgence canalisations",
    "description": "Débouchage à Belcodène (13720). Canalisations bouchées, sable, sel. Intervention rapide pour résidences secondaires et locations saisonnières.",
    "focus_keyword": "débouchage belcodène"
  },
  "content": "<h2>Débouchage à Belcodène : l'urgence estivale des résidences secondaires</h2><p>Belcodène compte 2009 habitants, mais ce chiffre triple en été. La commune accueille une population flottante de vacanciers et propriétaires de résidences secondaires qui arrivent sans prévenir. Quand une canalisation se bouche en juillet ou août, c'est une urgence : pas d'eau chaude, douche impraticable, toilettes bloquées. Les propriétaires non-résidents appellent depuis des centaines de kilomètres, paniqués.</p><p>La proximité relative avec le littoral méditerranéen crée un contexte particulier à Belcodène. Bien que la commune ne soit pas côtière, elle attire des vacanciers qui fuient les plages saturées de la région PACA. Les locations saisonnières se multiplient au Centre de Belcodène, particulièrement durant les mois d'été. Chaque nouveau locataire apporte son lot de problèmes : habitudes différentes, méconnaissance des installations locales, usage intensif de l'eau.</p><h2>L'assainissement sous pression : impacts du tourisme estival</h2><p>Les réseaux d'assainissement de Belcodène ne sont pas dimensionnés pour absorber une surcharge estivale de cette ampleur. Quand 600 à 800 personnes supplémentaires arrivent en deux semaines, les stations de traitement et les canalisations subissent une pression anormale. Les débits augmentent brutalement. Les tuyaux anciens, typiques des communes de cette taille en Provence, commencent à céder.</p><p>Au Centre de Belcodène, où se concentrent les locations touristiques, on observe un pic de débouchages entre juin et septembre. Les appels au plombier-déboucheur s'accumulent. Les délais s'allongent. Les propriétaires qui louent leur bien doivent gérer des situations critiques : un bouchon signifie une perte financière directe (remboursement aux locataires, perte de réservation), et donc une motivation très forte à résoudre le problème immédiatement.</p><h2>Sable, sel et détergents : les vrais ennemis des canalisations belcodéniennes</h2><p>Belcodène subit un problème très spécifique : l'accumulation de sable fin dans les canalisations. Les vacanciers revenant de plages proches déposent du sable dans les douches et lavabos. Ce sable, combiné à l'eau calcaire locale, forme des bouchons tenaces. Il s'accumule aux points bas des tuyauteries et crée des ralentissements chroniques.</p><p>Le sel marin constitue un second facteur de dégradation. Bien que Belcodène soit à 43.423°N et 5.585°E (pas en bord de mer direct), l'air salin pénètre les zones côtières avoisinantes, et les vacanciers apportent avec eux vêtements imbibés de sel. Celui-ci s'écoule lors des lessives intensives de l'été. Le sel accélère la corrosion des canalisations métalliques anciennes, fragilisant l'ensemble du réseau.</p><p>Les locataires saisonniers utilisent aussi des quantités massives de détergents, shampooings et savons. Ces résidus s'accumulent rapidement dans les coudes et rétrécissements des tuyaux. À Belcodène, où les rénovations complètes des réseaux restent limitées, on manipule souvent des sections de canalisation datant de 20 à 40 ans. Ces anciens tuyaux ont des parois rugueuses qui retiennent mieux les dépôts.</p><h2>Intervention dans les zones belcodéniennes : Centre et périphérie</h2><p>On intervient principalement au Centre de Belcodène, où se concentrent les habitations et les locations. C'est là que les débouchages sont les plus fréquents. Les tuyauteries communes de ce secteur acheminent l'eau de 50 à 100 logements. Un seul bouchon peut affecter plusieurs foyers simultanément.</p><p>La topographie locale influence aussi les problèmes. Belcodène s'étend sur un territoire avec des variations d'altitude. Certains secteurs du Centre présentent des canalisations avec peu de pente, ce qui ralentit l'évacuation des eaux grises. L'eau stagne plus longtemps, favorisant la consolidation des dépôts de sable et de calcaire.</p><p>Les communes voisines comme Gréasque, Peynier et Fuveau connaissent des problèmes similaires, mais Belcodène subit une intensité particulière à cause du tourisme de courte durée. Les vacanciers ne connaissent pas les bons gestes (pas de chiffons dans les toilettes, pas d'huile dans l'évier) et provoquent des dégâts dans des délais très courts.</p><h2>Locations saisonnières : urgence et contraintes horaires</h2><p>Pour un propriétaire qui loue son bien à Belcodène, un débouchage n'est jamais banal. C'est une intervention qui doit se faire en quelques heures, pas demain ou la semaine prochaine. Les locataires actuels ne peuvent pas rester sans eau courante. Le propriétaire doit rembourser la nuit ou payer une pénalité sur les plateformes de réservation.</p><p>On adapte donc les interventions aux contraintes de la location saisonnière. Il faut intervenir le jour même, souvent en fin d'après-midi. Les outils utilisés doivent être efficaces sans endommager les canalisations fragiles. Le déboucheur doit diagnostiquer rapidement : est-ce un bouchon simple (sable, cheveux) ou un problème structurel (fissure, effondrement) ? Pour une location, cette distinction est critique : un bouchon simple coûte 150 à 300 euros, un terrassement peut en coûter 2000.</p><p>Les propriétaires non-résidents ne peuvent pas vérifier l'état des canalisations eux-mêmes. Ils font confiance au diagnostic du professionnel. C'est pourquoi la transparence et la clarté des explications sont essentielles : le propriétaire doit comprendre exactement ce qui s'est passé et pourquoi l'intervention coûte ce prix.</p><p>Pour les locations répétitives (propriétaire qui remet son bien en location chaque été), on peut aussi proposer une visite préventive en juin, avant l'arrivée des premiers vacanciers. Nettoyer les canalisations et identifier les points faibles permet d'éviter les débouchages d'urgence en pleine saison.</p><h2>Questions fréquentes des propriétaires belcodéniens</h2>",
  "faq": [
    {
      "question": "Je loue ma maison à Belcodène l'été. Comment éviter les bouchons de canalisation ?",
      "answer": "Un nettoyage préventif des canalisations en mai ou juin limite les risques. Pendant la saison, insistez auprès des locataires pour qu'ils utilisent les canalisations correctement : pas de lingettes, pas d'huile, pas de cheveux. Si vous avez une piscine ou une douche extérieure à Belcodène, rincez-la régulièrement pour limiter l'accumulation de sable. Un déboucheur peut aussi vous proposer un contrat d'intervention prioritaire, avec intervention garantie sous 2-3 heures."
    },
    {
      "question": "Le sable des plages peut-il vraiment boucher mes tuyaux à Belcodène ?",
      "answer": "Absolument. Le sable fin s'accumule dans les siphons des douches et lavabos. Combiné à l'eau calcaire locale et aux résidus de savon, il forme une pâte solide. Au Centre de Belcodène, on observe régulièrement ce type de bouchon chez les propriétés proches des accès vers les plages côtières. Une grille ou un filtre sur la sortie de douche ralentit le phénomène, mais seul le nettoyage régulier élimine vraiment le problème."
    },
    {
      "question": "Quel est le délai d'intervention à Belcodène en juillet-août ?",
      "answer": "En pleine saison estivale, les demandes de débouchage à Belcodène augmentent fortement. On s'efforce de traiter les urgences (pas d'eau du tout, toilettes inutilisables) le jour même, mais il peut y avoir quelques heures d'attente. Pour les situations moins critiques, l'intervention peut avoir lieu le lendemain matin. Contactez rapidement : plus tôt on est informé, plus vite on peut planifier."
    }
  ],
  "internal_links": [
    {
      "slug": "debouchage-greasque",
      "label": "Débouchage Gréasque"
    },
    {
      "slug": "debouchage-peynier",
      "label": "Débouchage Peynier"
    },
    {
      "slug": "debouchage-fuveau",
      "label": "Débouchage Fuveau"
    },
    {
      "slug": "debouchage-peypin",
      "label": "Débouchage Peypin"
    },
    {
      "slug": "debouchage-la-bouilladisse",
      "label": "Débouchage La Bouilladisse"
    },
    {
      "slug": "debouchage-saint-savournin",
      "label": "Débouchage Saint-Savournin"
    }
  ],
  "quartiers": [
    "Le Centre"
  ],
  "word_count": 825,
  "schema": {}
}