{
  "title": "Debouchage Cuisine Saint-Raphaël (83530) — Intervention rapide",
  "slug": "debouchage-cuisine-saint-raphael",
  "type": "service-ville",
  "service": "debouchage-cuisine-saint-raphael",
  "ville": "Saint-Raphaël",
  "code_postal": "83530",
  "status": "draft",
  "meta": {
    "title": "Debouchage Cuisine Saint-Raphaël (83530) — Urgence 24h/7j",
    "description": "Évier de cuisine bouché à Saint-Raphaël (83530) ? Graisse, calcaire, résidus — intervention rapide 24h/7j. Devis gratuit au 06 27 69 91 34.",
    "focus_keyword": "debouchage cuisine Saint-Raphaël"
  },
  "content": "<h1>Debouchage cuisine à Saint-Raphaël (83530)</h1>\n\n<p>Évier de cuisine bouché à Saint-Raphaël ? L'eau stagne, les odeurs remontent, et rien ne passe malgré les tentatives ? On intervient dans l'heure pour déboucher votre cuisine, que vous soyez à Valescure, Boulouris, Santa Lucia, Le Dramont ou Agay. Appelez le <strong>06 27 69 91 34</strong> — on règle le problème sans détour.</p>\n\n<p>La cuisine est la pièce où les canalisations souffrent le plus. Graisses, huiles de cuisson, résidus alimentaires — tout finit dans l'évier. À Saint-Raphaël, le calcaire de l'eau aggrave la situation en cimentant les dépôts sur les parois. Dans les grandes cuisines équipées des villas de Valescure et Boulouris, les conduites sont longues et les graisses ont tout le temps de se figer avant d'atteindre le collecteur. Dans les locations saisonnières de Santa Lucia, c'est l'usage intensif estival qui précipite le bouchon.</p>\n\n<h2>Pourquoi la canalisation de cuisine se bouche à Saint-Raphaël</h2>\n\n<ul>\n<li><strong>Graisses figées</strong> — L'huile d'olive, le beurre, la graisse de cuisson — versés chauds dans l'évier, ils se figent dans la conduite en refroidissant. Couche après couche, le bouchon grossit. Dans les villas de Valescure, les conduites de cuisine peuvent faire dix mètres avant de rejoindre la colonne principale. La graisse a largement le temps de se solidifier.</li>\n<li><strong>Calcaire incrusté</strong> — L'eau dure de Saint-Raphaël dépose du tartre à l'intérieur des conduites. Le calcaire s'accroche aux dépôts de graisse et crée une couche dure, presque imperméable. C'est ce qui rend les bouchons de cuisine raphaëlois particulièrement résistants aux méthodes classiques.</li>\n<li><strong>Résidus alimentaires</strong> — Marc de café, épluchures, restes de repas, pâtes, riz — les résidus gonflent dans l'eau et se coincent dans le siphon ou les coudes de la conduite. Les locations de vacances sans broyeur ni grille sont les premières concernées.</li>\n<li><strong>Résidences secondaires : dépôts séchés</strong> — Après des mois de fermeture, les résidus de graisse et de calcaire dans les conduites des cuisines de Boulouris et du Dramont ont séché et durci. Le premier gros repas de vacances génère un flux de graisse qui vient se coller à ces dépôts et provoque le blocage total.</li>\n</ul>\n\n<h2>Comment on débouche votre cuisine à Saint-Raphaël</h2>\n\n<ol>\n<li><strong>Inspection du siphon</strong> — On démonte le siphon de l'évier pour évaluer l'état des conduites. Si le bouchon est là, on le retire et on nettoie. Rapide et économique.</li>\n<li><strong>Furet électrique</strong> — Pour les bouchons situés plus loin dans la conduite, le furet perce l'obstruction et la fragmente. Particulièrement efficace sur les amas de graisse molle.</li>\n<li><strong>Hydrocurage haute pression</strong> — C'est la méthode de référence pour les cuisines de Saint-Raphaël. Le jet haute pression émulsionne les graisses, décolle le calcaire et expulse tous les résidus. La conduite retrouve son diamètre d'origine. Indispensable pour les longues conduites des villas de Valescure.</li>\n<li><strong>Contrôle et conseils</strong> — On vérifie que l'écoulement est rapide et sans odeur. On vous donne les bons gestes pour limiter l'accumulation de graisse : ne jamais verser d'huile chaude, utiliser une grille, faire couler de l'eau chaude après la vaisselle.</li>\n</ol>\n\n<h2>Tarifs debouchage cuisine à Saint-Raphaël</h2>\n\n<ul>\n<li><strong>Debouchage siphon cuisine</strong> : à partir de 79 € TTC</li>\n<li><strong>Debouchage au furet</strong> : à partir de 89 € TTC</li>\n<li><strong>Hydrocurage conduite cuisine</strong> : à partir de 149 € TTC</li>\n</ul>\n\n<p>Tarif annoncé avant déplacement. Pas de frais cachés. Devis gratuit au <strong>06 27 69 91 34</strong>.</p>\n\n<h2>Communes voisines desservies</h2>\n\n<ul>\n<li><a href=\"/debouchage-cuisine-frejus/\">Debouchage cuisine Fréjus</a> — ville voisine, 5 minutes</li>\n<li><a href=\"/debouchage-puget-sur-argens/\">Debouchage cuisine Puget-sur-Argens</a> — 10 minutes</li>\n<li><a href=\"/debouchage-roquebrune-sur-argens/\">Debouchage cuisine Roquebrune-sur-Argens</a> — arrière-pays</li>\n<li><a href=\"/debouchage-les-adrets-de-l-esterel/\">Debouchage cuisine Les Adrets-de-l'Estérel</a> — 20 minutes</li>\n<li><a href=\"/debouchage-bagnols-en-foret/\">Debouchage cuisine Bagnols-en-Forêt</a> — 25 minutes</li>\n</ul>\n\n<h2>Questions fréquentes — Cuisine bouchée à Saint-Raphaël</h2>\n\n<p><strong>Le lave-vaisselle refoule quand l'évier est bouché. Les deux sont liés ?</strong><br>\nOui, dans la plupart des installations, le lave-vaisselle et l'évier partagent la même conduite d'évacuation. Quand cette conduite est bouchée, l'eau du lave-vaisselle n'a nulle part où aller et refoule par l'évier (ou inversement). Déboucher la conduite commune résout les deux problèmes en une seule intervention.</p>\n\n<p><strong>Combien de temps avant que la graisse rebouche la conduite après un debouchage ?</strong><br>\nAvec un hydrocurage complet, les conduites sont propres et le problème ne revient pas avant un à trois ans, selon votre usage. Si vous évitez de verser les graisses dans l'évier et que vous faites couler de l'eau chaude régulièrement, l'intervalle peut être bien plus long. Pour les villas de Valescure avec des conduites longues, un curage annuel préventif est le meilleur investissement.</p>\n\n<p><strong>Je gère une location saisonnière à Saint-Raphaël. Quand faut-il faire entretenir la cuisine ?</strong><br>\nAvant la saison, idéalement en mai ou début juin. Un curage préventif de la conduite de cuisine élimine les graisses et le calcaire accumulés pendant l'hiver. Ça évite l'urgence du samedi soir en plein mois d'août quand l'évier refoule pendant que les locataires préparent le dîner. On propose des contrats d'entretien adaptés aux propriétaires de locations.</p>\n\n<h2>Cuisine bouchée à Saint-Raphaël ? Appelez maintenant</h2>\n\n<p>On intervient dans tous les quartiers : Valescure, Boulouris, Le Dramont, Santa Lucia, Agay et le centre-ville. Disponible 24h/7j, devis gratuit.</p>\n\n<p>Appelez le <strong><a href=\"tel:0627699134\">06 27 69 91 34</a></strong> ou consultez <a href=\"https://entreprisededebouchage.com\">entreprisededebouchage.com</a>.</p>",
  "faq": [
    {
      "question": "Le lave-vaisselle refoule quand l'évier est bouché. Les deux sont liés ?",
      "answer": "Oui, dans la plupart des installations, le lave-vaisselle et l'évier partagent la même conduite d'évacuation. Déboucher la conduite commune résout les deux problèmes en une seule intervention."
    },
    {
      "question": "Combien de temps avant que la graisse rebouche la conduite après un debouchage ?",
      "answer": "Avec un hydrocurage complet, le problème ne revient pas avant un à trois ans selon votre usage. Évitez de verser les graisses dans l'évier et faites couler de l'eau chaude régulièrement."
    },
    {
      "question": "Je gère une location saisonnière à Saint-Raphaël. Quand faut-il faire entretenir la cuisine ?",
      "answer": "Avant la saison, idéalement en mai ou début juin. Un curage préventif élimine les graisses et le calcaire accumulés pendant l'hiver. On propose des contrats d'entretien adaptés aux propriétaires de locations."
    }
  ],
  "internal_links": [
    {"slug": "debouchage-cuisine-frejus", "label": "Debouchage cuisine Fréjus"},
    {"slug": "debouchage-puget-sur-argens", "label": "Debouchage Puget-sur-Argens"},
    {"slug": "debouchage-roquebrune-sur-argens", "label": "Debouchage Roquebrune-sur-Argens"},
    {"slug": "debouchage-les-adrets-de-l-esterel", "label": "Debouchage Les Adrets-de-l'Estérel"},
    {"slug": "debouchage-bagnols-en-foret", "label": "Debouchage Bagnols-en-Forêt"}
  ],
  "word_count": 880,
  "quartiers": ["Valescure", "Boulouris", "Le Dramont", "Santa Lucia", "Agay"]
}