{
  "title": "Débouchage Roquevaire 13360 — Intervention 24h/24 canalisation bouchée",
  "slug": "debouchage-roquevaire",
  "type": "ville",
  "ville": "Roquevaire",
  "code_postal": "13360",
  "status": "published",
  "meta": {
    "title": "Débouchage Roquevaire 13360 — Intervention rapide 24h",
    "description": "Débouchage canalisation à Roquevaire (13360). Urgence été, sable, sel. Intervention immédiate. Propriétaires résidents et non-résidents.",
    "focus_keyword": "débouchage roquevaire"
  },
  "content": "<h2>Débouchage à Roquevaire : la saisonnalité estivale met les réseaux sous pression</h2><p>Roquevaire accueille une population de 8915 habitants, augmentée considérablement durant l'été par les résidents secondaires et les touristes. Cette commune des Bouches-du-Rhône, située à 43.345°N et 5.598°E, bénéficie d'une proximité avec le littoral méditerranéen qui en fait une destination attractive. Mais cette affluence saisonnière expose les canalisations à des contraintes exceptionnelles.</p><p>Entre juillet et août, les locataires saisonniers utilisent intensivement eau chaude, chasses d'eau et douches. Les réseaux d'assainissement de Roquevaire subissent des pics de débit qu'ils ne connaissent pas le reste de l'année. Les bouchons apparaissent à ce moment-là, souvent quand on ne s'y attend pas : un dimanche soir, un jour férié, en pleine nuit.</p><h2>Impact du tourisme sur l'assainissement roquevairien</h2><p>Au Centre de Roquevaire, comme dans les petites communes tournées vers l'accueil estival, les réseaux collectifs datent parfois des années 1970-1980. Ils n'ont pas été dimensionnés pour supporter une multiplication par deux ou trois de la charge hydrique. Les communes voisines — La Destrousse, Peypin, Auriol, La Bouilladisse, Aubagne, Gémenos — rencontrent les mêmes problèmes saisonniers.</p><p>Le tourisme génère aussi une consommation différente : les visiteurs ne connaissent pas les écogestes locaux. Papier toilette jeté sans modération, restes alimentaires non-compostés, cheveux accumulés dans les douches. Les canalisations privées se bouchent plus souvent en haute saison.</p><h2>Sable et sel : les ennemis spécifiques des canalisations côtières</h2><p>Roquevaire n'est pas en première ligne côtière, mais sa proximité avec la mer signifie que le sable transporté par l'air s'infiltre dans les réseaux d'assainissement. Il s'accumule au fil du temps dans les portions horizontales des tuyaux. Le sel marin, même en petites quantités, accélère la corrosion des anciennes canalisations en fonte.</p><p>Les joints et les coudes deviennent poreux. Des micro-fissures apparaissent. L'eau s'écoule moins vite. Les dépôts s'y accumulent davantage. C'est un cycle dégradatif typique des zones soumises à l'influence méditerranéenne.</p><h2>Débouchage au Centre de Roquevaire et zones résidentielles</h2><p>Au Centre, où se concentre la vie administrative et commerciale, on intervient sur des immeubles anciens avec des canalisations en fonte verticales. Les branchements individuels vers le tout-à-l'égout souffrent de dépôts calcaires qui s'ajoutent au sable et aux graisses. Une canalisation bouchée au Centre peut bloquer plusieurs habitations si elle affecte une portion commune.</p><p>Les zones résidentielles périphériques, où vivent les propriétaires permanents, présentent des réseaux plus modernes mais également sujets aux problèmes estivaux. Les locations saisonnières y sont nombreuses : petites maisons individuelles transformées en gîtes, appartements loués meublés par les propriétaires non-résidents.</p><h2>Intervention en location saisonnière : urgence et responsabilité</h2><p>Pour un propriétaire non-résident de Roquevaire, la canalisation bouchée en pleine saison touristique est une catastrophe. Les locataires signalent le problème à distance. On doit intervenir rapidement, sans quoi l'eau remonte dans la baignoire, la machine à laver s'arrête, la situation devient intenable.</p><p>Le diagnostic doit être précis : est-ce un bouchon situé dans le branchement privé (responsabilité du propriétaire) ou dans la canalisation collective (responsabilité de la commune) ? À Roquevaire, cette distinction est fondamentale pour déterminer qui assume le coût de l'intervention et les réparations éventuelles.</p><p>On dispose de méthodes adaptées : débouchage manuel avec furet, hydrocurage haute pression, intervention au déboucheur pneumatique. On ne démolit pas le carrelage si une simple intervention tuyauterie suffit. Le locataire peut rester logé et l'activité touristique ne s'interrompt pas.</p><h2>Débouchage d'urgence 24h/24 à Roquevaire</h2><p>Les canalisations ne choisissent pas leurs horaires de dysfonctionnement. Un bouchon survient généralement en fin d'après-midi, quand les locataires rentrent de la plage, quand la pression d'utilisation est maximale. On intervient aussi les dimanches, les jours fériés, la nuit. Roquevaire mérite un service réactif, surtout en période estivale.</p><p>Le diagnostic se déroule en deux étapes : première visite pour identifier le bouchon à l'œil ou avec une micro-caméra, proposition de solution, puis débouchage effectif. Pour les propriétaires non-résidents, on peut envoyer un rapport photo-vidéo montrant avant/après l'intervention.</p><h2>Prévention et entretien des canalisations roquevairennes</h2><p>Un débouchage curatif coûte plus cher qu'un entretien préventif. Pour les locations saisonnières à Roquevaire, on recommande un passage hydrocurage annuel avant la saison estivale. Cela prévient les bouchons, réduit les mauvaises odeurs, assure une évacuation optimale.</p><p>Les vieilles canalisations en fonte, fréquentes au Centre, bénéficient d'une inspection caméra avant travaux. Si la canalisation est partiellement dégradée, un simple débouchage est inutile : on doit prévoir un remplacement. On peut alors proposer une rénovation sans fouille, avec tubage résine.</p><h2>Service local reconnu dans les Bouches-du-Rhône</h2><p>On connaît bien les spécificités de Roquevaire et des communes environnantes : La Destrousse, Peypin, Auriol, La Bouilladisse, Aubagne, Gémenos. Le terrain, l'âge des réseaux, les matériaux utilisés localement, tout cela influence le diagnostic et le choix de la méthode de débouchage.</p><p>Les propriétaires comme les locataires à Roquevaire savent que l'été, c'est la haute saison pour les bouchons. On en tient compte dans l'organisation du planning. Pas de fausses promesses : juste une intervention rapide, efficace et un suivi après travaux si nécessaire.</p>",
  "faq": [
    {
      "question": "Mon gîte à Roquevaire est bouché un samedi soir en juillet : comment je fais ?",
      "answer": "On intervient 24h/24, y compris les weekends et jours fériés. Contactez-nous en ligne ou par téléphone dès que vous détectez le problème. On se déplace pour un diagnostic immédiat et on procède au débouchage sur place. Pour un propriétaire non-résident, un rapport photo-vidéo confirme l'intervention."
    },
    {
      "question": "Est-ce que le sable marin bouche vraiment les canalisations à Roquevaire ?",
      "answer": "Oui, même si Roquevaire n'est pas en bord de mer. Le sable transporté par l'air s'accumule dans les tuyaux, surtout les portions horizontales. Combiné au sel qui corrode la fonte ancienne, c'est un problème courant ici. Un entretien annuel par hydrocurage avant l'été réduit ce risque."
    },
    {
      "question": "Ma canalisation au Centre est bouchée : comment vous savez si c'est mon branchement ou la commune ?",
      "answer": "On inspecte avec une micro-caméra. Si le bouchon se situe entre votre habitation et le regard public, c'est votre responsabilité. Si c'est au-delà, c'est celle de la commune. On vous explique clairement après diagnostic et on vous aide à identifier le bon interlocuteur."
    }
  ],
  "internal_links": [
    {
      "slug": "debouchage-la-destrousse",
      "label": "Débouchage La Destrousse"
    },
    {
      "slug": "debouchage-peypin",
      "label": "Débouchage Peypin"
    },
    {
      "slug": "debouchage-auriol",
      "label": "Débouchage Auriol"
    },
    {
      "slug": "debouchage-la-bouilladisse",
      "label": "Débouchage La Bouilladisse"
    },
    {
      "slug": "debouchage-aubagne",
      "label": "Débouchage Aubagne"
    },
    {
      "slug": "debouchage-gemenos",
      "label": "Débouchage Gémenos"
    }
  ],
  "quartiers": [
    "Le Centre"
  ],
  "word_count": 817,
  "schema": {}
}