{
  "title": "Débouchage Éguilles 13510 — Intervention urgente canalisations",
  "slug": "debouchage-eguilles",
  "type": "ville",
  "ville": "Éguilles",
  "code_postal": "13510",
  "status": "published",
  "meta": {
    "title": "Débouchage Éguilles 13510 — Intervention urgente 24h/24",
    "description": "Débouchage canalisations à Éguilles (13510). Intervention d'urgence sur tuyauterie bouchée. Sable, sel, surcharge estivale. Devis sur place.",
    "focus_keyword": "débouchage Éguilles"
  },
  "content": "<h2>Débouchage à Éguilles : urgence saisonnière en banlieue d'Aix</h2><p>Éguilles compte 8 479 habitants et joue le rôle de commune-dortoir pour les actifs d'Aix-en-Provence. Mais chaque été, la situation change. Les résidences secondaires se remplissent, les locations saisonnières affichent complet, et les réseaux d'assainissement du Centre subissent une pression anormale. Les propriétaires non-résidents découvrent souvent les problèmes trop tard : un débouchage devient alors une course contre la montre.</p><p>La proximité relative avec la côte méditerranéenne (moins de 80 km) influence aussi les problèmes rencontrés à Éguilles. Même sans être littoral, le sel et le sable remontent dans les canalisations via les eaux de ruissellement et les apports externes. Les vacanciers stockent du matériel de plage, vidangent des seaux d'eau salée dans les lavabos, et les réseaux souterrains s'encrassent plus vite qu'en hiver.</p><h2>Impact du tourisme d'été sur l'assainissement</h2><p>Entre juin et septembre, Éguilles voit défiler des centaines de visiteurs. Les locations saisonnières du Centre et des alentours tournent à plein régime. Or, ces logements, souvent anciens ou mal entretenus en dehors de la saison touristique, accumulent les défauts invisibles : joints usés, tuyauterie calcifiée, dépôts de graisse jamais nettoyés.</p><p>La surcharge estivale crée un appel d'air systématique : plus d'occupants = plus de consommation = plus de pression sur des réseaux dimensionnés pour une occupation hivernale réduite. Les canalisations du Centre d'Éguilles, en particulier, subissent des engorgements répétés entre juillet et août. Un simple bouchon mineur devient bloquant en trois jours.</p><h2>Problèmes spécifiques : sable, sel et urgence locataire</h2><p>Le sable s'infiltre via les terrasses, les cours, les jardins. Il descend vers les canalisations par les eaux pluviales mal séparées. À Éguilles, zone semi-rurale, le contrôle des eaux de pluie reste inégal. Le sel provient des adoucisseurs d'eau des résidences secondaires, des détergents marins ramenés par les vacanciers, et des eaux de nettoyage de voitures.</p><p>Cette combinaison sable + sel + graisse restaurée + calcaire crée des bouchons tenaces. Contrairement aux bouchons organiques purs, ces dépôts mixtes résistent aux déboucheurs classiques. Il faut intervenir avec une stratégie adaptée : hydrocurage, câble rotative, ou inspection vidéo pour bien identifier la nature et la localisation du bouchon.</p><p>L'urgence pour un propriétaire à distance est réelle : si la canalisation d'une location saisonnière se bouche en plein mois d'août, cela signifie trois jours sans eau potable pour les locataires, des avis négatifs, une dépense imprévue, et potentiellement une action en responsabilité civile.</p><h2>Intervention dans le Centre et périphérie d'Éguilles</h2><p>Le Centre d'Éguilles regroupe la majorité des commerces, services et habitations. C'est la zone de plus forte densité et, logiquement, de plus forte demande d'intervention en débouchage. Les immeubles collectifs y sont concentrés, avec des colonnes montantes partagées où un seul bouchon crée des refoulements en cascade.</p><p>On intervient aussi sur les quartiers et hameaux alentours. Les communes voisines comme Ventabren, Coudoux, et Saint-Cannat subissent les mêmes cycles touristiques. Mais Éguilles bénéficie d'une accessibilité directe depuis les axes routiers majeurs : en cas d'urgence déclarée avant 11h, une intervention le jour même reste possible.</p><h2>Interventions en location saisonnière : contraintes et solutions</h2><p>Louer un bien à Éguilles sur AirBnB ou de façon traditionnelle implique une gestion des risques hydrauliques. Les locataires n'ont aucune formation sur les gestes à éviter. Résultat : papier toilette en excès, essuie-tout, produits cosmétiques, restes alimentaires solidifiés descendent allègrement dans les tuyauteries.</p><p>La solution passe par trois points : un diagnostic préventif avant la première saison (qui révèle les points faibles), une information écrite aux locataires (affichage aux points d'eau), et un numéro d'urgence unique pour débouchage. Bloquer une évacuation en plein mois d'août à Éguilles, c'est bloquer le chiffre d'affaires et la réputation d'un propriétaire.</p><p>Pour les propriétaires non-résidents, on propose une intervention d'inspection vidéo en début de saison (mai), suivie d'un hydrocurage préventif. Cette approche coûte moins qu'une urgence débouchage en juillet et protège le bien durablement.</p><h2>FAQ débouchage Éguilles</h2><ul><li><strong>Peut-on déboucher une canalisation bouchée sans casser le carrelage à Éguilles ?</strong><br/>Oui. L'inspection vidéo par caméra thermique permet de localiser précisément le bouchon, puis on utilise l'hydrocurage ou le câble rotative par un accès existant (baignoire, douche). Si vraiment il faut casser, on le dit à l'avance et on cherche d'abord par des voies non-invasives.</li><li><strong>Combien de temps il faut pour déboucher une canalisation à Éguilles, centre-ville ?</strong><br/>Entre 30 minutes et 2 heures selon la nature du bouchon. Un simple cheveu/savon : 30 min. Un dépôt sable-sel-calcaire : 1h30 à 2h. On évalue sur place après inspection vidéo rapide.</li><li><strong>Qui paie le débouchage en location saisonnière si c'est l'occupant qui a bouché ?</strong><br/>C'est au contrat. En général, si c'est un usage normal (pas de jet de béton dans la tuyauterie), c'est au propriétaire/bailleur via son assurance responsabilité civile. Mieux vaut assurer la prévention que de disputer la facture en fin d'été.</li></ul>",
  "faq": [
    {
      "question": "Peut-on déboucher une canalisation bouchée sans casser le carrelage à Éguilles ?",
      "answer": "Oui. L'inspection vidéo par caméra thermique permet de localiser précisément le bouchon, puis on utilise l'hydrocurage ou le câble rotative par un accès existant (baignoire, douche). Si vraiment il faut casser, on le dit à l'avance et on cherche d'abord par des voies non-invasives."
    },
    {
      "question": "Combien de temps il faut pour déboucher une canalisation à Éguilles, centre-ville ?",
      "answer": "Entre 30 minutes et 2 heures selon la nature du bouchon. Un simple cheveu/savon : 30 min. Un dépôt sable-sel-calcaire : 1h30 à 2h. On évalue sur place après inspection vidéo rapide."
    },
    {
      "question": "Qui paie le débouchage en location saisonnière si c'est l'occupant qui a bouché ?",
      "answer": "C'est au contrat. En général, si c'est un usage normal (pas de jet de béton dans la tuyauterie), c'est au propriétaire/bailleur via son assurance responsabilité civile. Mieux vaut assurer la prévention que de disputer la facture en fin d'été."
    }
  ],
  "internal_links": [
    {
      "slug": "debouchage-ventabren",
      "label": "Débouchage Ventabren"
    },
    {
      "slug": "debouchage-coudoux",
      "label": "Débouchage Coudoux"
    },
    {
      "slug": "debouchage-saint-cannat",
      "label": "Débouchage Saint-Cannat"
    },
    {
      "slug": "debouchage-aix-en-provence",
      "label": "Débouchage Aix-en-Provence"
    },
    {
      "slug": "debouchage-velaux",
      "label": "Débouchage Velaux"
    },
    {
      "slug": "debouchage-la-fare-les-oliviers",
      "label": "Débouchage La Fare-les-Oliviers"
    }
  ],
  "quartiers": [
    "Le Centre"
  ],
  "word_count": 797,
  "schema": {}
}